[{"id":3687,"owner":"osteele","name":"lztestkit","fullRepoName":"osteele/lztestkit","mainLanguage":"JavaScript","sizeInBytes":152,"createdAt":"2008-03-12T21:58:06Z","updatedAt":"2018-06-23T20:12:47Z","forkCount":0,"livetimeInDays":3952,"contributers":[{"name":"osteele","totalSize":30}],"topics":["testing-framework","bdd","open-laszlo","bdd-framework"],"usedLanguages":[{"name":"JavaScript","sizeInBytes":46062}]},{"id":6233,"owner":"HusseinMorsy","name":"railsbuch_theme","fullRepoName":"HusseinMorsy/railsbuch_theme","mainLanguage":null,"sizeInBytes":148,"createdAt":"2008-04-02T07:32:25Z","updatedAt":"2017-08-06T22:55:46Z","forkCount":1,"livetimeInDays":3931,"contributers":[{"name":"ajnato","totalSize":1},{"name":"HusseinMorsy","totalSize":21}],"topics":["rails","book","learning"],"usedLanguages":[]},{"id":1948,"owner":"osteele","name":"sequentially","fullRepoName":"osteele/sequentially","mainLanguage":"JavaScript","sizeInBytes":130,"createdAt":"2008-03-01T00:36:32Z","updatedAt":"2018-06-23T18:40:30Z","forkCount":1,"livetimeInDays":3963,"contributers":[{"name":"osteele","totalSize":41}],"topics":["javascript-library","functional-programming","reactive-programming"],"usedLanguages":[{"name":"JavaScript","sizeInBytes":24492}]},{"id":7085,"owner":"osteele","name":"lzosutils","fullRepoName":"osteele/lzosutils","mainLanguage":"JavaScript","sizeInBytes":199,"createdAt":"2008-04-05T02:07:02Z","updatedAt":"2018-06-23T18:45:57Z","forkCount":2,"livetimeInDays":3928,"contributers":[{"name":"osteele","totalSize":146}],"topics":["open-laszlo","flash","library"],"usedLanguages":[{"name":"JavaScript","sizeInBytes":82369}]},{"id":46498,"owner":"jasonrudolph","name":"bending-gorm","fullRepoName":"jasonrudolph/bending-gorm","mainLanguage":"Groovy","sizeInBytes":6467,"createdAt":"2008-08-27T03:22:02Z","updatedAt":"2018-12-31T12:09:29Z","forkCount":3,"livetimeInDays":3784,"contributers":[],"topics":["groovy","grails","presentation","slides"],"usedLanguages":[{"name":"Groovy","sizeInBytes":22881},{"name":"Java","sizeInBytes":10744},{"name":"JavaScript","sizeInBytes":1865}]},{"id":46507,"owner":"jasonrudolph","name":"getting-started-with-grails","fullRepoName":"jasonrudolph/getting-started-with-grails","mainLanguage":"Groovy","sizeInBytes":6340,"createdAt":"2008-08-27T03:49:53Z","updatedAt":"2018-12-31T12:11:18Z","forkCount":6,"livetimeInDays":3784,"contributers":[{"name":"jasonrudolph","totalSize":1}],"topics":["groovy","grails","presentation","slides"],"usedLanguages":[{"name":"Groovy","sizeInBytes":4672},{"name":"JavaScript","sizeInBytes":373}]},{"id":49870,"owner":"puzza007","name":"openpoker","fullRepoName":"puzza007/openpoker","mainLanguage":"Erlang","sizeInBytes":168,"createdAt":"2008-09-06T13:51:51Z","updatedAt":"2018-03-15T08:59:07Z","forkCount":16,"livetimeInDays":3774,"contributers":[],"topics":["erlang","poker-engine","poker"],"usedLanguages":[{"name":"Erlang","sizeInBytes":263951}]},{"id":61210,"owner":"davep","name":"mandeldraw","fullRepoName":"davep/mandeldraw","mainLanguage":null,"sizeInBytes":88,"createdAt":"2008-10-09T15:38:31Z","updatedAt":"2016-05-08T14:38:05Z","forkCount":1,"livetimeInDays":3741,"contributers":[],"topics":["ocaml","mandelbrot","mandelbrot-fractal","fractal"],"usedLanguages":[]},{"id":93415,"owner":"jrbedard","name":"real-time-raytracer","fullRepoName":"jrbedard/real-time-raytracer","mainLanguage":"C++","sizeInBytes":144,"createdAt":"2008-12-19T03:39:13Z","updatedAt":"2016-09-15T20:26:51Z","forkCount":1,"livetimeInDays":3670,"contributers":[],"topics":["c-plus-plus","raytracer","raytracing","raytracing-engine"],"usedLanguages":[{"name":"C++","sizeInBytes":34466}]},{"id":46495,"owner":"jasonrudolph","name":"going-further-with-grails","fullRepoName":"jasonrudolph/going-further-with-grails","mainLanguage":"Groovy","sizeInBytes":6497,"createdAt":"2008-08-27T03:18:31Z","updatedAt":"2018-12-31T12:11:52Z","forkCount":5,"livetimeInDays":3784,"contributers":[],"topics":["groovy","grails","presentation","slides"],"usedLanguages":[{"name":"Groovy","sizeInBytes":97672},{"name":"Java","sizeInBytes":30843},{"name":"JavaScript","sizeInBytes":373}]},{"id":111657,"owner":"nathanpitman","name":"paid_members.ext.ee_addon","fullRepoName":"nathanpitman/paid_members.ext.ee_addon","mainLanguage":"PHP","sizeInBytes":75,"createdAt":"2009-01-21T08:53:10Z","updatedAt":"2017-04-27T09:37:26Z","forkCount":2,"livetimeInDays":3637,"contributers":[],"topics":["expressionengine","eecms","plugin"],"usedLanguages":[{"name":"PHP","sizeInBytes":16386}]},{"id":124915,"owner":"jmbr","name":"callgraph","fullRepoName":"jmbr/callgraph","mainLanguage":null,"sizeInBytes":76,"createdAt":"2009-02-09T12:16:10Z","updatedAt":"2017-04-14T22:49:10Z","forkCount":1,"livetimeInDays":3618,"contributers":[],"topics":["debugging-tool","awk","bash"],"usedLanguages":[]},{"id":125677,"owner":"jmbr","name":"gnostic","fullRepoName":"jmbr/gnostic","mainLanguage":null,"sizeInBytes":336,"createdAt":"2009-02-10T09:38:23Z","updatedAt":"2017-02-25T16:39:40Z","forkCount":1,"livetimeInDays":3617,"contributers":[],"topics":["blackboard","security-audit","utility"],"usedLanguages":[]},{"id":108161,"owner":"davorg","name":"newsfeeds","fullRepoName":"davorg/newsfeeds","mainLanguage":null,"sizeInBytes":88,"createdAt":"2009-01-15T17:24:50Z","updatedAt":"2017-02-20T11:12:33Z","forkCount":0,"livetimeInDays":3643,"contributers":[],"topics":["perl","rss","atom","web-feeds","opengl","news"],"usedLanguages":[]},{"id":151414,"owner":"HusseinMorsy","name":"i18_simple_demo","fullRepoName":"HusseinMorsy/i18_simple_demo","mainLanguage":"Ruby","sizeInBytes":172,"createdAt":"2009-03-15T17:05:53Z","updatedAt":"2017-08-06T23:04:32Z","forkCount":0,"livetimeInDays":3584,"contributers":[],"topics":["ruby","rails","book","learning"],"usedLanguages":[{"name":"Ruby","sizeInBytes":19272},{"name":"JavaScript","sizeInBytes":148}]},{"id":9521,"owner":"osteele","name":"jcon","fullRepoName":"osteele/jcon","mainLanguage":"Ruby","sizeInBytes":104,"createdAt":"2008-04-14T01:09:49Z","updatedAt":"2018-06-23T20:14:36Z","forkCount":0,"livetimeInDays":3919,"contributers":[],"topics":["json","json-schema","ruby-gems"],"usedLanguages":[{"name":"Ruby","sizeInBytes":21349}]},{"id":158924,"owner":"x6j8x","name":"erlaws","fullRepoName":"x6j8x/erlaws","mainLanguage":"Erlang","sizeInBytes":82,"createdAt":"2009-03-25T09:34:17Z","updatedAt":"2018-01-25T12:36:26Z","forkCount":37,"livetimeInDays":3574,"contributers":[],"topics":["erlang","aws","abandoned"],"usedLanguages":[{"name":"Erlang","sizeInBytes":55503}]},{"id":161434,"owner":"osteele","name":"openlaszlo-rails-example","fullRepoName":"osteele/openlaszlo-rails-example","mainLanguage":"Ruby","sizeInBytes":188,"createdAt":"2009-03-28T01:29:45Z","updatedAt":"2018-06-23T18:42:42Z","forkCount":0,"livetimeInDays":3571,"contributers":[],"topics":["rails","example","open-laszlo"],"usedLanguages":[{"name":"Ruby","sizeInBytes":15323},{"name":"JavaScript","sizeInBytes":283}]},{"id":174087,"owner":"davorg","name":"data-tree","fullRepoName":"davorg/data-tree","mainLanguage":null,"sizeInBytes":80,"createdAt":"2009-04-12T14:51:33Z","updatedAt":"2017-02-20T11:12:44Z","forkCount":1,"livetimeInDays":3556,"contributers":[],"topics":["perl","data","tree"],"usedLanguages":[]},{"id":174089,"owner":"davorg","name":"html-menu","fullRepoName":"davorg/html-menu","mainLanguage":null,"sizeInBytes":84,"createdAt":"2009-04-12T14:54:47Z","updatedAt":"2017-02-20T11:12:59Z","forkCount":1,"livetimeInDays":3556,"contributers":[],"topics":["perl","html","menu"],"usedLanguages":[]},{"id":174094,"owner":"davorg","name":"template-plugin-html-menu","fullRepoName":"davorg/template-plugin-html-menu","mainLanguage":null,"sizeInBytes":92,"createdAt":"2009-04-12T15:06:37Z","updatedAt":"2017-02-20T11:13:46Z","forkCount":0,"livetimeInDays":3556,"contributers":[],"topics":["perl","html","menu","template","tt"],"usedLanguages":[]},{"id":180307,"owner":"nathanpitman","name":"reading_time.pi.ee_addon","fullRepoName":"nathanpitman/reading_time.pi.ee_addon","mainLanguage":"PHP","sizeInBytes":77,"createdAt":"2009-04-19T21:24:56Z","updatedAt":"2017-04-27T09:36:58Z","forkCount":0,"livetimeInDays":3549,"contributers":[],"topics":["expressionengine","eecms","plugin"],"usedLanguages":[{"name":"PHP","sizeInBytes":2496}]},{"id":4115,"owner":"osteele","name":"openlaszlo_plugin","fullRepoName":"osteele/openlaszlo_plugin","mainLanguage":"JavaScript","sizeInBytes":467,"createdAt":"2008-03-16T18:13:37Z","updatedAt":"2018-06-23T18:42:00Z","forkCount":1,"livetimeInDays":3948,"contributers":[],"topics":["rails-plugins","open-laszlo","rails"],"usedLanguages":[{"name":"JavaScript","sizeInBytes":23602},{"name":"Ruby","sizeInBytes":20032}]},{"id":190359,"owner":"osteele","name":"protodoc","fullRepoName":"osteele/protodoc","mainLanguage":"JavaScript","sizeInBytes":460,"createdAt":"2009-05-01T19:09:56Z","updatedAt":"2018-06-23T20:16:02Z","forkCount":1,"livetimeInDays":3537,"contributers":[],"topics":["documentation-tool","documentation-generator","obsolete"],"usedLanguages":[{"name":"JavaScript","sizeInBytes":43224}]},{"id":128200,"owner":"ahf","name":"irssi-lua","fullRepoName":"ahf/irssi-lua","mainLanguage":"C","sizeInBytes":120,"createdAt":"2009-02-13T14:46:06Z","updatedAt":"2018-02-16T00:47:14Z","forkCount":1,"livetimeInDays":3614,"contributers":[],"topics":["irssi","lua-bindings","irc"],"usedLanguages":[{"name":"C","sizeInBytes":29748}]},{"id":172631,"owner":"davorg","name":"ubiquity","fullRepoName":"davorg/ubiquity","mainLanguage":"JavaScript","sizeInBytes":80,"createdAt":"2009-04-10T09:29:18Z","updatedAt":"2017-02-20T11:14:22Z","forkCount":0,"livetimeInDays":3558,"contributers":[],"topics":["javascript","ubiquity","search"],"usedLanguages":[{"name":"JavaScript","sizeInBytes":1080}]},{"id":214929,"owner":"rhcarvalho","name":"monothello","fullRepoName":"rhcarvalho/monothello","mainLanguage":"Python","sizeInBytes":100,"createdAt":"2009-05-31T18:26:20Z","updatedAt":"2018-09-26T14:38:51Z","forkCount":1,"livetimeInDays":3507,"contributers":[],"topics":["python","game","tk","tkinter"],"usedLanguages":[{"name":"Python","sizeInBytes":15042}]},{"id":222711,"owner":"rhcarvalho","name":"popclock","fullRepoName":"rhcarvalho/popclock","mainLanguage":"Python","sizeInBytes":256,"createdAt":"2009-06-09T15:17:20Z","updatedAt":"2014-07-14T17:37:47Z","forkCount":1,"livetimeInDays":3498,"contributers":[],"topics":["python","clock","pygame"],"usedLanguages":[{"name":"Python","sizeInBytes":12371},{"name":"Shell","sizeInBytes":142}]},{"id":221254,"owner":"rhcarvalho","name":"SimplePythonChatter","fullRepoName":"rhcarvalho/SimplePythonChatter","mainLanguage":"Python","sizeInBytes":112,"createdAt":"2009-06-08T02:14:28Z","updatedAt":"2018-07-21T03:23:47Z","forkCount":1,"livetimeInDays":3499,"contributers":[],"topics":["python","gtk","twisted","client-server"],"usedLanguages":[{"name":"Python","sizeInBytes":65513}]},{"id":278405,"owner":"wtnabe","name":"vbox_tools","fullRepoName":"wtnabe/vbox_tools","mainLanguage":"Ruby","sizeInBytes":88,"createdAt":"2009-08-15T01:37:25Z","updatedAt":"2017-05-08T14:34:23Z","forkCount":0,"livetimeInDays":3431,"contributers":[],"topics":["ruby","rubygems","deprecated","vagrant"],"usedLanguages":[{"name":"Ruby","sizeInBytes":6951}]},{"id":280309,"owner":"ahf","name":"twelf-syntax","fullRepoName":"ahf/twelf-syntax","mainLanguage":"VimL","sizeInBytes":72,"createdAt":"2009-08-17T20:21:11Z","updatedAt":"2018-02-16T14:47:11Z","forkCount":0,"livetimeInDays":3429,"contributers":[],"topics":["vim","vim-script","vim-plugin","twelf"],"usedLanguages":[{"name":"Vim script","sizeInBytes":2182}]},{"id":154164,"owner":"mort","name":"twitterlikker","fullRepoName":"mort/twitterlikker","mainLanguage":"JavaScript","sizeInBytes":80,"createdAt":"2009-03-19T10:50:31Z","updatedAt":"2018-10-29T15:43:03Z","forkCount":0,"livetimeInDays":3580,"contributers":[],"topics":["twitter","greasemonkey","likes","throwback"],"usedLanguages":[{"name":"JavaScript","sizeInBytes":4375},{"name":"Ruby","sizeInBytes":1696}]},{"id":292513,"owner":"cheshire137","name":"Coach","fullRepoName":"cheshire137/Coach","mainLanguage":"Ruby","sizeInBytes":176,"createdAt":"2009-08-30T16:34:22Z","updatedAt":"2018-08-10T19:27:09Z","forkCount":0,"livetimeInDays":3416,"contributers":[],"topics":["rails-application","football","video-storage"],"usedLanguages":[{"name":"Ruby","sizeInBytes":17899},{"name":"JavaScript","sizeInBytes":148}]},{"id":298203,"owner":"karentamrazyan","name":"OpenPIM","fullRepoName":"karentamrazyan/OpenPIM","mainLanguage":"PHP","sizeInBytes":92,"createdAt":"2009-09-05T05:58:00Z","updatedAt":"2017-10-14T23:10:53Z","forkCount":1,"livetimeInDays":3410,"contributers":[],"topics":["pim","personal-information-management","contacts","bookmarks","todo","todos","tasks","productivity"],"usedLanguages":[{"name":"PHP","sizeInBytes":36643}]},{"id":95247,"owner":"szastupov","name":"lgears","fullRepoName":"szastupov/lgears","mainLanguage":"Scheme","sizeInBytes":744,"createdAt":"2008-12-22T10:16:26Z","updatedAt":"2017-10-04T06:27:58Z","forkCount":1,"livetimeInDays":3667,"contributers":[],"topics":["scheme","c","lisp"],"usedLanguages":[{"name":"Scheme","sizeInBytes":142595},{"name":"C","sizeInBytes":68184}]},{"id":276579,"owner":"agustingianni","name":"StreamingProject","fullRepoName":"agustingianni/StreamingProject","mainLanguage":"C","sizeInBytes":96,"createdAt":"2009-08-13T01:09:16Z","updatedAt":"2018-07-18T12:44:57Z","forkCount":2,"livetimeInDays":3433,"contributers":[],"topics":["streaming","mp3","server"],"usedLanguages":[{"name":"C","sizeInBytes":38719},{"name":"Shell","sizeInBytes":75}]},{"id":317712,"owner":"sunaku","name":"ofc2_to_png","fullRepoName":"sunaku/ofc2_to_png","mainLanguage":"JavaScript","sizeInBytes":380,"createdAt":"2009-09-25T19:40:12Z","updatedAt":"2018-01-14T22:14:44Z","forkCount":0,"livetimeInDays":3390,"contributers":[],"topics":["chart-framework","image-converter","headless"],"usedLanguages":[{"name":"JavaScript","sizeInBytes":67474},{"name":"Ruby","sizeInBytes":6244},{"name":"Shell","sizeInBytes":327}]},{"id":124778,"owner":"sunaku","name":"rassmalog","fullRepoName":"sunaku/rassmalog","mainLanguage":"Ruby","sizeInBytes":708,"createdAt":"2009-02-09T06:37:28Z","updatedAt":"2018-01-14T22:07:57Z","forkCount":1,"livetimeInDays":3618,"contributers":[],"topics":["blog-engine","static-site-generator","yaml-configuration"],"usedLanguages":[{"name":"Ruby","sizeInBytes":39907}]},{"id":343028,"owner":"filipp","name":"MediaRelay","fullRepoName":"filipp/MediaRelay","mainLanguage":"Python","sizeInBytes":76,"createdAt":"2009-10-20T03:12:07Z","updatedAt":"2018-04-18T08:00:04Z","forkCount":0,"livetimeInDays":3365,"contributers":[],"topics":["ftp","file-upload","file-sharing"],"usedLanguages":[{"name":"Python","sizeInBytes":3542}]},{"id":285760,"owner":"simonboots","name":"OpenSteerCUDA","fullRepoName":"simonboots/OpenSteerCUDA","mainLanguage":"C++","sizeInBytes":1065,"createdAt":"2009-08-23T16:29:44Z","updatedAt":"2018-02-28T03:20:23Z","forkCount":1,"livetimeInDays":3423,"contributers":[],"topics":["cuda","c-plus-plus","gpgpu-computing"],"usedLanguages":[{"name":"C++","sizeInBytes":477186},{"name":"C","sizeInBytes":21325}]},{"id":289824,"owner":"wtnabe","name":"shlauncher","fullRepoName":"wtnabe/shlauncher","mainLanguage":"Ruby","sizeInBytes":96,"createdAt":"2009-08-27T13:04:41Z","updatedAt":"2017-05-08T14:37:10Z","forkCount":0,"livetimeInDays":3419,"contributers":[],"topics":["ruby","rubygems","deprecated"],"usedLanguages":[{"name":"Ruby","sizeInBytes":9849}]},{"id":355183,"owner":"KTamas","name":"netpincer_hacks","fullRepoName":"KTamas/netpincer_hacks","mainLanguage":"JavaScript","sizeInBytes":76,"createdAt":"2009-10-30T11:18:54Z","updatedAt":"2017-03-29T11:15:29Z","forkCount":0,"livetimeInDays":3355,"contributers":[],"topics":["javascript","bookmarklet","bookmarklets","netpincer","old","unmaintained-dont-use"],"usedLanguages":[{"name":"JavaScript","sizeInBytes":2809}]},{"id":371006,"owner":"briandoll","name":"st-elsewhere","fullRepoName":"briandoll/st-elsewhere","mainLanguage":"Ruby","sizeInBytes":102,"createdAt":"2009-11-13T01:17:12Z","updatedAt":"2018-08-14T21:48:24Z","forkCount":15,"livetimeInDays":3341,"contributers":[],"topics":["activerecord","ruby","database-connector"],"usedLanguages":[{"name":"Ruby","sizeInBytes":7784}]},{"id":387893,"owner":"tobiassjosten","name":"ansicolor","fullRepoName":"tobiassjosten/ansicolor","mainLanguage":null,"sizeInBytes":76,"createdAt":"2009-11-27T22:33:51Z","updatedAt":"2017-03-22T14:42:01Z","forkCount":0,"livetimeInDays":3326,"contributers":[],"topics":["php","ansi","cli"],"usedLanguages":[]},{"id":392145,"owner":"LindseyB","name":"minorProjects","fullRepoName":"LindseyB/minorProjects","mainLanguage":"C#","sizeInBytes":300,"createdAt":"2009-12-01T23:48:02Z","updatedAt":"2018-10-31T20:20:33Z","forkCount":0,"livetimeInDays":3322,"contributers":[],"topics":["c","data-structures","c-sharp","java"],"usedLanguages":[{"name":"C#","sizeInBytes":23718},{"name":"C","sizeInBytes":12133},{"name":"C++","sizeInBytes":9922},{"name":"Java","sizeInBytes":8176},{"name":"Python","sizeInBytes":3026}]},{"id":402091,"owner":"KTamas","name":"ubiquity-hu","fullRepoName":"KTamas/ubiquity-hu","mainLanguage":"JavaScript","sizeInBytes":121,"createdAt":"2009-12-06T15:54:50Z","updatedAt":"2017-03-29T11:05:58Z","forkCount":1,"livetimeInDays":3318,"contributers":[],"topics":["ubiquity","old","javascript","unmaintained-dont-use"],"usedLanguages":[{"name":"JavaScript","sizeInBytes":108871}]},{"id":409775,"owner":"howardjp","name":"daemon","fullRepoName":"howardjp/daemon","mainLanguage":"C","sizeInBytes":76,"createdAt":"2009-12-09T04:58:38Z","updatedAt":"2015-09-23T12:45:52Z","forkCount":0,"livetimeInDays":3315,"contributers":[],"topics":["daemon","unix","bsd","command-line-tool","job-control"],"usedLanguages":[{"name":"C","sizeInBytes":721}]},{"id":409778,"owner":"howardjp","name":"write","fullRepoName":"howardjp/write","mainLanguage":"C","sizeInBytes":104,"createdAt":"2009-12-09T05:00:47Z","updatedAt":"2015-01-29T20:10:23Z","forkCount":0,"livetimeInDays":3315,"contributers":[],"topics":["unix","linux","write","network-communications","inetd","command-line-tool","phone"],"usedLanguages":[{"name":"C","sizeInBytes":18622}]},{"id":394959,"owner":"howardjp","name":"uwatch","fullRepoName":"howardjp/uwatch","mainLanguage":"C","sizeInBytes":84,"createdAt":"2009-12-04T03:30:17Z","updatedAt":"2015-01-29T20:10:21Z","forkCount":0,"livetimeInDays":3320,"contributers":[],"topics":["user-management","command-line-tool","bsd","m-net"],"usedLanguages":[{"name":"C","sizeInBytes":8376}]},{"id":409776,"owner":"howardjp","name":"rpt","fullRepoName":"howardjp/rpt","mainLanguage":"C","sizeInBytes":76,"createdAt":"2009-12-09T04:59:23Z","updatedAt":"2015-01-29T20:10:22Z","forkCount":0,"livetimeInDays":3315,"contributers":[],"topics":["bsd","repeat","watch","command-line-tool"],"usedLanguages":[{"name":"C","sizeInBytes":2176}]},{"id":439832,"owner":"howardjp","name":"lx","fullRepoName":"howardjp/lx","mainLanguage":"PHP","sizeInBytes":112,"createdAt":"2009-12-16T22:31:31Z","updatedAt":"2016-07-05T18:50:04Z","forkCount":0,"livetimeInDays":3307,"contributers":[],"topics":["cakephp","link-shortener","incomplete"],"usedLanguages":[{"name":"PHP","sizeInBytes":47555}]},{"id":309459,"owner":"lfborjas","name":"micro_ada","fullRepoName":"lfborjas/micro_ada","mainLanguage":"Java","sizeInBytes":9504,"createdAt":"2009-09-17T03:50:14Z","updatedAt":"2018-10-29T02:54:57Z","forkCount":1,"livetimeInDays":3398,"contributers":[],"topics":["java","compilers","ada95"],"usedLanguages":[{"name":"Java","sizeInBytes":1340162},{"name":"Vim script","sizeInBytes":6002},{"name":"Emacs Lisp","sizeInBytes":2559},{"name":"ActionScript","sizeInBytes":387}]},{"id":445652,"owner":"filipp","name":"FinalStore","fullRepoName":"filipp/FinalStore","mainLanguage":"Shell","sizeInBytes":420,"createdAt":"2009-12-22T08:59:04Z","updatedAt":"2017-10-19T07:53:07Z","forkCount":1,"livetimeInDays":3302,"contributers":[],"topics":["media-library","final-cut-server","final-cut-pro","digital-asset-management","archiware"],"usedLanguages":[{"name":"Shell","sizeInBytes":3446},{"name":"Python","sizeInBytes":2040}]},{"id":458407,"owner":"jonhoo","name":"Clean-Output","fullRepoName":"jonhoo/Clean-Output","mainLanguage":"PHP","sizeInBytes":77,"createdAt":"2010-01-04T19:28:50Z","updatedAt":"2013-11-27T20:57:14Z","forkCount":0,"livetimeInDays":3289,"contributers":[],"topics":["php","html","tidy","formatting","pretty-print"],"usedLanguages":[{"name":"PHP","sizeInBytes":19844}]},{"id":411850,"owner":"NIA","name":"D3DBumpMapping","fullRepoName":"NIA/D3DBumpMapping","mainLanguage":"C++","sizeInBytes":1780,"createdAt":"2009-12-09T19:42:54Z","updatedAt":"2017-08-17T14:07:50Z","forkCount":0,"livetimeInDays":3315,"contributers":[],"topics":["computer-graphics","directx","university-project"],"usedLanguages":[{"name":"C++","sizeInBytes":49049}]},{"id":27732,"owner":"dryruby","name":"crm114.rb","fullRepoName":"dryruby/crm114.rb","mainLanguage":"Ruby","sizeInBytes":97,"createdAt":"2008-06-23T10:46:17Z","updatedAt":"2018-09-12T10:08:13Z","forkCount":6,"livetimeInDays":3849,"contributers":[],"topics":["obsolete","unmaintained","ruby","rubygems"],"usedLanguages":[{"name":"Ruby","sizeInBytes":8109}]},{"id":466747,"owner":"limal","name":"nit","fullRepoName":"limal/nit","mainLanguage":"C++","sizeInBytes":108,"createdAt":"2010-01-10T22:49:20Z","updatedAt":"2018-09-13T11:29:50Z","forkCount":0,"livetimeInDays":3282,"contributers":[],"topics":["c-plus-plus","directx","directx-9","3d-graphics-renderer"],"usedLanguages":[{"name":"C++","sizeInBytes":54530}]},{"id":480897,"owner":"dryruby","name":"php.rb","fullRepoName":"dryruby/php.rb","mainLanguage":"Ruby","sizeInBytes":175,"createdAt":"2010-01-20T17:34:50Z","updatedAt":"2018-12-10T16:49:11Z","forkCount":21,"livetimeInDays":3273,"contributers":[],"topics":["obsolete","unmaintained","ruby","rubygems"],"usedLanguages":[{"name":"Ruby","sizeInBytes":58935}]},{"id":485744,"owner":"przemoc","name":"abe","fullRepoName":"przemoc/abe","mainLanguage":null,"sizeInBytes":84,"createdAt":"2010-01-24T00:52:46Z","updatedAt":"2017-03-27T22:30:00Z","forkCount":2,"livetimeInDays":3269,"contributers":[],"topics":["linux","boot","grub"],"usedLanguages":[]},{"id":496005,"owner":"yageek","name":"Mandel","fullRepoName":"yageek/Mandel","mainLanguage":"C","sizeInBytes":76,"createdAt":"2010-01-31T10:21:05Z","updatedAt":"2018-01-10T18:12:50Z","forkCount":0,"livetimeInDays":3262,"contributers":[],"topics":["c","mandelbrot-fractal","sdl"],"usedLanguages":[{"name":"C","sizeInBytes":2004}]},{"id":495744,"owner":"cheshire137","name":"GithubFacebook","fullRepoName":"cheshire137/GithubFacebook","mainLanguage":"Ruby","sizeInBytes":1235,"createdAt":"2010-01-31T02:45:18Z","updatedAt":"2018-08-10T19:27:02Z","forkCount":1,"livetimeInDays":3262,"contributers":[],"topics":["rails-application","facebook","github"],"usedLanguages":[{"name":"Ruby","sizeInBytes":19530},{"name":"JavaScript","sizeInBytes":12136}]},{"id":508622,"owner":"andatche","name":"centos-grub","fullRepoName":"andatche/centos-grub","mainLanguage":null,"sizeInBytes":1092,"createdAt":"2010-02-08T22:34:01Z","updatedAt":"2017-11-13T14:41:21Z","forkCount":0,"livetimeInDays":3253,"contributers":[],"topics":["centos","grub","gpt"],"usedLanguages":[]},{"id":221115,"owner":"jlaffaye","name":"btpd-cgi","fullRepoName":"jlaffaye/btpd-cgi","mainLanguage":"C","sizeInBytes":104,"createdAt":"2009-06-07T20:55:55Z","updatedAt":"2017-01-12T06:14:08Z","forkCount":1,"livetimeInDays":3500,"contributers":[],"topics":["btpd","frontend","torrent"],"usedLanguages":[{"name":"C","sizeInBytes":10541},{"name":"C#","sizeInBytes":3444},{"name":"C++","sizeInBytes":1085}]},{"id":426735,"owner":"timjb","name":"MooSweeper","fullRepoName":"timjb/MooSweeper","mainLanguage":"JavaScript","sizeInBytes":256,"createdAt":"2009-12-12T17:27:41Z","updatedAt":"2017-11-08T16:26:24Z","forkCount":0,"livetimeInDays":3312,"contributers":[],"topics":["minesweeper","javascript-library","mootools"],"usedLanguages":[{"name":"JavaScript","sizeInBytes":122606}]},{"id":509228,"owner":"stuartcarnie","name":"c64iphone","fullRepoName":"stuartcarnie/c64iphone","mainLanguage":"Objective-C","sizeInBytes":5078,"createdAt":"2010-02-09T08:12:51Z","updatedAt":"2018-04-05T04:29:15Z","forkCount":15,"livetimeInDays":3253,"contributers":[],"topics":["objective-c","emulator","ios"],"usedLanguages":[{"name":"Objective-C","sizeInBytes":2388863},{"name":"C","sizeInBytes":502605},{"name":"C++","sizeInBytes":232983}]},{"id":851563,"owner":"flightaware","name":"flightxml-client-ruby","fullRepoName":"flightaware/flightxml-client-ruby","mainLanguage":"Ruby","sizeInBytes":80,"createdAt":"2010-08-20T16:33:23Z","updatedAt":"2017-02-24T18:01:01Z","forkCount":1,"livetimeInDays":3061,"contributers":[],"topics":["flightxml","ruby","aviation","flightaware-flightxml-service"],"usedLanguages":[]},{"id":535308,"owner":"KTamas","name":"ireketmondunk","fullRepoName":"KTamas/ireketmondunk","mainLanguage":"Ruby","sizeInBytes":15108,"createdAt":"2010-02-25T07:58:43Z","updatedAt":"2017-03-29T11:05:35Z","forkCount":0,"livetimeInDays":3237,"contributers":[],"topics":["ruby","jruby","appengine","unmaintained-dont-use","twitter-bot"],"usedLanguages":[{"name":"Ruby","sizeInBytes":1151}]},{"id":321177,"owner":"agustingianni","name":"ffuzzer","fullRepoName":"agustingianni/ffuzzer","mainLanguage":"C","sizeInBytes":132,"createdAt":"2009-09-29T15:35:04Z","updatedAt":"2018-01-18T22:41:30Z","forkCount":0,"livetimeInDays":3386,"contributers":[],"topics":["fuzzing","fuzzer","filesystem"],"usedLanguages":[{"name":"C","sizeInBytes":72966},{"name":"Python","sizeInBytes":3801}]},{"id":642564,"owner":"KTamas","name":"joaos","fullRepoName":"KTamas/joaos","mainLanguage":"Ruby","sizeInBytes":92,"createdAt":"2010-05-02T13:49:00Z","updatedAt":"2017-03-29T11:04:38Z","forkCount":0,"livetimeInDays":3171,"contributers":[],"topics":["showoff","ruby","presentation","old","meetup"],"usedLanguages":[{"name":"Ruby","sizeInBytes":34}]},{"id":448869,"owner":"sshaw","name":"transform_legacy_attribute_methods","fullRepoName":"sshaw/transform_legacy_attribute_methods","mainLanguage":"Ruby","sizeInBytes":92,"createdAt":"2009-12-25T10:20:58Z","updatedAt":"2018-01-13T16:59:34Z","forkCount":3,"livetimeInDays":3299,"contributers":[],"topics":["ruby","activerecord","legacy","database"],"usedLanguages":[{"name":"Ruby","sizeInBytes":5361}]},{"id":660065,"owner":"sesam","name":"FolderdateFollowsFiles","fullRepoName":"sesam/FolderdateFollowsFiles","mainLanguage":"Visual Basic","sizeInBytes":660,"createdAt":"2010-05-11T01:56:11Z","updatedAt":"2018-01-08T13:18:46Z","forkCount":0,"livetimeInDays":3162,"contributers":[],"topics":["net","samba-share","visual-basic"],"usedLanguages":[{"name":"Visual Basic","sizeInBytes":20127}]},{"id":615472,"owner":"cbrecabarren","name":"gme","fullRepoName":"cbrecabarren/gme","mainLanguage":"C","sizeInBytes":188,"createdAt":"2010-04-17T20:38:43Z","updatedAt":"2018-09-24T17:22:44Z","forkCount":1,"livetimeInDays":3186,"contributers":[],"topics":["ruby","c","snes","extension","spc","game-music-emu"],"usedLanguages":[{"name":"C","sizeInBytes":15969},{"name":"Ruby","sizeInBytes":6378},{"name":"C++","sizeInBytes":1357}]},{"id":38272,"owner":"ariya","name":"pictureflow","fullRepoName":"ariya/pictureflow","mainLanguage":"C++","sizeInBytes":134,"createdAt":"2008-07-29T16:38:46Z","updatedAt":"2018-12-07T18:50:43Z","forkCount":10,"livetimeInDays":3813,"contributers":[],"topics":["c-plus-plus","qt","widget","3-d","coverflow","pictureflow"],"usedLanguages":[{"name":"C++","sizeInBytes":36157},{"name":"Python","sizeInBytes":1256}]},{"id":675080,"owner":"cfleschhut","name":"Simple-jQuery-Slideshow","fullRepoName":"cfleschhut/Simple-jQuery-Slideshow","mainLanguage":"JavaScript","sizeInBytes":640,"createdAt":"2010-05-19T13:35:11Z","updatedAt":"2017-04-25T23:21:35Z","forkCount":0,"livetimeInDays":3154,"contributers":[],"topics":["javascript","jquery","css","xhtml","slideshow"],"usedLanguages":[{"name":"JavaScript","sizeInBytes":1213}]},{"id":677309,"owner":"cfleschhut","name":"Simple-jQuery-Tabs","fullRepoName":"cfleschhut/Simple-jQuery-Tabs","mainLanguage":null,"sizeInBytes":96,"createdAt":"2010-05-20T15:34:39Z","updatedAt":"2017-04-25T23:21:00Z","forkCount":0,"livetimeInDays":3153,"contributers":[],"topics":["javascript","jquery","css","xhtml","tabs"],"usedLanguages":[]},{"id":670903,"owner":"ia","name":"battery-status","fullRepoName":"ia/battery-status","mainLanguage":"Python","sizeInBytes":147,"createdAt":"2010-05-17T13:01:20Z","updatedAt":"2018-11-29T16:13:31Z","forkCount":2,"livetimeInDays":3156,"contributers":[],"topics":["python","gtk2","pygtk","gnome2","appindicator","usability","ux","laptop","powermanagement","bonobo","notify","notify-osd"],"usedLanguages":[{"name":"Python","sizeInBytes":956}]},{"id":698731,"owner":"noroot","name":"scripts","fullRepoName":"noroot/scripts","mainLanguage":null,"sizeInBytes":96,"createdAt":"2010-06-02T06:54:12Z","updatedAt":"2018-12-15T13:46:11Z","forkCount":0,"livetimeInDays":3140,"contributers":[],"topics":["ruby","redmine","jira"],"usedLanguages":[]},{"id":692435,"owner":"floehopper","name":"installd-client","fullRepoName":"floehopper/installd-client","mainLanguage":"Ruby","sizeInBytes":996,"createdAt":"2010-05-29T10:12:22Z","updatedAt":"2018-08-19T11:16:00Z","forkCount":0,"livetimeInDays":3144,"contributers":[],"topics":["rubycocoa","ruby","macos","ios","iphone","social-network"],"usedLanguages":[{"name":"Ruby","sizeInBytes":35777},{"name":"C","sizeInBytes":8145},{"name":"Objective-C","sizeInBytes":2886},{"name":"Shell","sizeInBytes":128}]},{"id":382905,"owner":"howardjp","name":"freegrep","fullRepoName":"howardjp/freegrep","mainLanguage":"C","sizeInBytes":408,"createdAt":"2009-11-23T19:19:48Z","updatedAt":"2018-01-22T18:42:50Z","forkCount":3,"livetimeInDays":3331,"contributers":[],"topics":["regular-expression","grep","bsd","pattern-matching"],"usedLanguages":[{"name":"C","sizeInBytes":41474}]},{"id":717240,"owner":"splitbrain","name":"irfc","fullRepoName":"splitbrain/irfc","mainLanguage":null,"sizeInBytes":108,"createdAt":"2010-06-12T12:19:49Z","updatedAt":"2016-08-09T15:06:01Z","forkCount":0,"livetimeInDays":3130,"contributers":[],"topics":["perl","lirc","menu"],"usedLanguages":[]},{"id":717308,"owner":"splitbrain","name":"pam-require","fullRepoName":"splitbrain/pam-require","mainLanguage":"C","sizeInBytes":152,"createdAt":"2010-06-12T13:28:35Z","updatedAt":"2016-08-09T15:05:56Z","forkCount":0,"livetimeInDays":3130,"contributers":[],"topics":["c","pam","authorization","pam-module"],"usedLanguages":[{"name":"C","sizeInBytes":6469}]},{"id":717327,"owner":"splitbrain","name":"navilink","fullRepoName":"splitbrain/navilink","mainLanguage":"Perl","sizeInBytes":136,"createdAt":"2010-06-12T13:49:38Z","updatedAt":"2016-10-02T21:23:35Z","forkCount":0,"livetimeInDays":3130,"contributers":[],"topics":["perl","gps","navilink","locosys"],"usedLanguages":[{"name":"Perl","sizeInBytes":22903}]},{"id":684995,"owner":"janlelis","name":"gedit-external-tools","fullRepoName":"janlelis/gedit-external-tools","mainLanguage":"Shell","sizeInBytes":818,"createdAt":"2010-05-25T11:29:29Z","updatedAt":"2018-10-06T16:07:29Z","forkCount":2,"livetimeInDays":3148,"contributers":[],"topics":["shell","ruby","gedit"],"usedLanguages":[{"name":"Shell","sizeInBytes":7662},{"name":"Ruby","sizeInBytes":4440}]},{"id":476375,"owner":"rhcarvalho","name":"sound_alarm","fullRepoName":"rhcarvalho/sound_alarm","mainLanguage":"Python","sizeInBytes":96,"createdAt":"2010-01-17T18:44:18Z","updatedAt":"2014-12-24T21:20:10Z","forkCount":0,"livetimeInDays":3276,"contributers":[],"topics":["python","midi","sounds","fun"],"usedLanguages":[{"name":"Python","sizeInBytes":8708}]},{"id":775588,"owner":"jstoker","name":"BasicBot","fullRepoName":"jstoker/BasicBot","mainLanguage":"Python","sizeInBytes":88,"createdAt":"2010-07-14T22:19:02Z","updatedAt":"2017-04-23T08:11:08Z","forkCount":1,"livetimeInDays":3097,"contributers":[],"topics":["python","irc","obsolete","do-not-use"],"usedLanguages":[{"name":"Python","sizeInBytes":871}]},{"id":773299,"owner":"Mischback","name":"PredatorButtons","fullRepoName":"Mischback/PredatorButtons","mainLanguage":"Lua","sizeInBytes":96,"createdAt":"2010-07-13T21:05:56Z","updatedAt":"2018-03-15T11:56:37Z","forkCount":0,"livetimeInDays":3099,"contributers":[],"topics":["lua","worldofwarcraft","world-of-warcraft","not-maintained","outdated"],"usedLanguages":[{"name":"Lua","sizeInBytes":13997}]},{"id":777188,"owner":"sukhchander","name":"cloudera-hadoop-ec2-spot","fullRepoName":"sukhchander/cloudera-hadoop-ec2-spot","mainLanguage":"Python","sizeInBytes":184,"createdAt":"2010-07-15T17:46:11Z","updatedAt":"2018-10-29T17:28:59Z","forkCount":2,"livetimeInDays":3097,"contributers":[],"topics":["aws","python","hadoop","ec2"],"usedLanguages":[{"name":"Python","sizeInBytes":83217},{"name":"Shell","sizeInBytes":31203},{"name":"JavaScript","sizeInBytes":10726}]},{"id":328996,"owner":"claus","name":"fc64","fullRepoName":"claus/fc64","mainLanguage":"ActionScript","sizeInBytes":1097,"createdAt":"2009-10-06T21:23:57Z","updatedAt":"2018-10-05T16:12:28Z","forkCount":7,"livetimeInDays":3379,"contributers":[],"topics":["actionscript","c64","emulator","6502","6510"],"usedLanguages":[{"name":"ActionScript","sizeInBytes":542087}]},{"id":741865,"owner":"mupimenov","name":"wibi","fullRepoName":"mupimenov/wibi","mainLanguage":"PHP","sizeInBytes":172,"createdAt":"2010-06-26T14:23:15Z","updatedAt":"2017-03-17T09:28:52Z","forkCount":0,"livetimeInDays":3116,"contributers":[],"topics":["php","blog-engine","mysql"],"usedLanguages":[{"name":"PHP","sizeInBytes":142602},{"name":"JavaScript","sizeInBytes":2304}]},{"id":794929,"owner":"mstn","name":"NXTServer","fullRepoName":"mstn/NXTServer","mainLanguage":"Java","sizeInBytes":124,"createdAt":"2010-07-24T10:49:57Z","updatedAt":"2018-12-05T00:00:48Z","forkCount":1,"livetimeInDays":3088,"contributers":[],"topics":["lego-mindstorms","lejos","restful"],"usedLanguages":[{"name":"Java","sizeInBytes":28343}]},{"id":782537,"owner":"DaHoC","name":"dschwarm","fullRepoName":"DaHoC/dschwarm","mainLanguage":"Java","sizeInBytes":100,"createdAt":"2010-07-18T20:47:08Z","updatedAt":"2018-12-18T13:16:07Z","forkCount":0,"livetimeInDays":3094,"contributers":[],"topics":["java","machine-learning","evolutionary-algorithms"],"usedLanguages":[{"name":"Java","sizeInBytes":11830}]},{"id":779139,"owner":"flightaware","name":"flightxml2-client-ruby","fullRepoName":"flightaware/flightxml2-client-ruby","mainLanguage":"Ruby","sizeInBytes":92,"createdAt":"2010-07-16T16:12:52Z","updatedAt":"2018-03-26T22:50:50Z","forkCount":3,"livetimeInDays":3096,"contributers":[],"topics":["flightxml","ruby","flightaware-flightxml-service"],"usedLanguages":[{"name":"Ruby","sizeInBytes":109189}]},{"id":780726,"owner":"DaHoC","name":"mlp","fullRepoName":"DaHoC/mlp","mainLanguage":"Java","sizeInBytes":292,"createdAt":"2010-07-17T18:13:18Z","updatedAt":"2018-12-18T13:15:31Z","forkCount":0,"livetimeInDays":3095,"contributers":[],"topics":["java","multi-layer-perceptron","machine-learning-algorithms"],"usedLanguages":[{"name":"Java","sizeInBytes":39914}]},{"id":801511,"owner":"splitbrain","name":"amazonwatch","fullRepoName":"splitbrain/amazonwatch","mainLanguage":"PHP","sizeInBytes":104,"createdAt":"2010-07-27T21:09:15Z","updatedAt":"2016-04-15T18:46:37Z","forkCount":0,"livetimeInDays":3085,"contributers":[],"topics":["php","amazon","amazon-product-advertising","price-tracker","rss","rss-generator"],"usedLanguages":[{"name":"PHP","sizeInBytes":27281}]},{"id":304423,"owner":"cybernet","name":"CyBerFuN-CoDeX","fullRepoName":"cybernet/CyBerFuN-CoDeX","mainLanguage":"PHP","sizeInBytes":20029,"createdAt":"2009-09-11T20:07:28Z","updatedAt":"2017-10-25T07:32:43Z","forkCount":6,"livetimeInDays":3404,"contributers":[],"topics":["php","torrent","tracker","mysql","outdated"],"usedLanguages":[{"name":"PHP","sizeInBytes":10813868},{"name":"JavaScript","sizeInBytes":926778}]},{"id":179151,"owner":"dryruby","name":"rakefile","fullRepoName":"dryruby/rakefile","mainLanguage":"Ruby","sizeInBytes":112,"createdAt":"2009-04-18T07:46:00Z","updatedAt":"2018-09-12T10:09:32Z","forkCount":1,"livetimeInDays":3550,"contributers":[],"topics":["obsolete","unmaintained","ruby","rubygems"],"usedLanguages":[{"name":"Ruby","sizeInBytes":3453}]},{"id":99666,"owner":"gaving","name":"vimmpc","fullRepoName":"gaving/vimmpc","mainLanguage":"Python","sizeInBytes":218,"createdAt":"2009-01-02T11:06:49Z","updatedAt":"2018-11-03T02:00:38Z","forkCount":1,"livetimeInDays":3656,"contributers":[],"topics":["vim","python","mpd"],"usedLanguages":[{"name":"Python","sizeInBytes":20855},{"name":"Vim script","sizeInBytes":1860},{"name":"Shell","sizeInBytes":26}]},{"id":785408,"owner":"Mischback","name":"Buffology","fullRepoName":"Mischback/Buffology","mainLanguage":"Lua","sizeInBytes":116,"createdAt":"2010-07-19T22:05:43Z","updatedAt":"2018-03-15T11:57:07Z","forkCount":0,"livetimeInDays":3092,"contributers":[],"topics":["lua","world-of-warcraft","worldofwarcraft","not-maintained","outdated"],"usedLanguages":[{"name":"Lua","sizeInBytes":38084}]},{"id":817831,"owner":"gergoerdi","name":"brainfuck-cpu","fullRepoName":"gergoerdi/brainfuck-cpu","mainLanguage":null,"sizeInBytes":156,"createdAt":"2010-08-04T20:38:02Z","updatedAt":"2017-02-08T02:43:17Z","forkCount":0,"livetimeInDays":3077,"contributers":[],"topics":["brainfuck","microprocessor","logisim","cpu"],"usedLanguages":[]},{"id":835149,"owner":"sunaku","name":"knights-tour","fullRepoName":"sunaku/knights-tour","mainLanguage":"C","sizeInBytes":112,"createdAt":"2010-08-13T06:04:47Z","updatedAt":"2018-01-14T22:09:12Z","forkCount":0,"livetimeInDays":3068,"contributers":[],"topics":["heuristic-search-algorithms","parallel-computing","gpu-acceleration"],"usedLanguages":[{"name":"C","sizeInBytes":14845}]},{"id":100159,"owner":"gaving","name":"vimtips","fullRepoName":"gaving/vimtips","mainLanguage":null,"sizeInBytes":1552,"createdAt":"2009-01-03T10:55:48Z","updatedAt":"2018-04-30T06:30:18Z","forkCount":4,"livetimeInDays":3655,"contributers":[],"topics":["vim","tips","vimtutor","latex","vimrc"],"usedLanguages":[]},{"id":844848,"owner":"LinuxDoku","name":"PHP-Plugin-System","fullRepoName":"LinuxDoku/PHP-Plugin-System","mainLanguage":null,"sizeInBytes":94,"createdAt":"2010-08-17T21:48:03Z","updatedAt":"2018-01-20T08:30:52Z","forkCount":5,"livetimeInDays":3063,"contributers":[],"topics":["php","plugin","plugin-manager"],"usedLanguages":[]},{"id":847429,"owner":"Mischback","name":"PredatorLoot","fullRepoName":"Mischback/PredatorLoot","mainLanguage":"Lua","sizeInBytes":100,"createdAt":"2010-08-18T22:39:29Z","updatedAt":"2018-03-15T11:57:42Z","forkCount":0,"livetimeInDays":3062,"contributers":[],"topics":["lua","world-of-warcraft","worldofwarcraft","not-maintained"],"usedLanguages":[{"name":"Lua","sizeInBytes":20112}]},{"id":791285,"owner":"branch14","name":"gentle","fullRepoName":"branch14/gentle","mainLanguage":"Ruby","sizeInBytes":108,"createdAt":"2010-07-22T16:04:19Z","updatedAt":"2018-07-11T07:22:37Z","forkCount":0,"livetimeInDays":3090,"contributers":[],"topics":["rails","template-engine","templating","ruby","nokogiri","railtie"],"usedLanguages":[{"name":"Ruby","sizeInBytes":8936}]},{"id":864575,"owner":"Stemby","name":"xkeyval-tutorial","fullRepoName":"Stemby/xkeyval-tutorial","mainLanguage":null,"sizeInBytes":96,"createdAt":"2010-08-26T17:58:10Z","updatedAt":"2018-11-17T04:19:24Z","forkCount":0,"livetimeInDays":3055,"contributers":[],"topics":["latex","xkeyval","tutorial","key-value","italian"],"usedLanguages":[]},{"id":582211,"owner":"oncletom","name":"uwa-vcub","fullRepoName":"oncletom/uwa-vcub","mainLanguage":"PHP","sizeInBytes":284,"createdAt":"2010-03-27T14:40:38Z","updatedAt":"2018-05-14T06:10:37Z","forkCount":0,"livetimeInDays":3207,"contributers":[],"topics":["bike-sharing","widget","bordeaux"],"usedLanguages":[{"name":"PHP","sizeInBytes":1631}]},{"id":433146,"owner":"saschpe","name":"masonry","fullRepoName":"saschpe/masonry","mainLanguage":"C++","sizeInBytes":1204,"createdAt":"2009-12-13T15:57:10Z","updatedAt":"2018-08-21T19:43:17Z","forkCount":0,"livetimeInDays":3311,"contributers":[],"topics":["c-plus-plus","qt","cmake","mason-graph"],"usedLanguages":[{"name":"C++","sizeInBytes":63160},{"name":"Objective-C","sizeInBytes":21019},{"name":"C","sizeInBytes":20761},{"name":"PHP","sizeInBytes":3382}]},{"id":731737,"owner":"nicolas-raoul","name":"Struts2CmisExplorer","fullRepoName":"nicolas-raoul/Struts2CmisExplorer","mainLanguage":"Java","sizeInBytes":4071,"createdAt":"2010-06-21T09:54:36Z","updatedAt":"2017-12-15T14:52:15Z","forkCount":1,"livetimeInDays":3121,"contributers":[],"topics":["cmis","cmis-client","web-app"],"usedLanguages":[{"name":"Java","sizeInBytes":42293}]},{"id":499382,"owner":"voy","name":"google-sidebar","fullRepoName":"voy/google-sidebar","mainLanguage":"JavaScript","sizeInBytes":128,"createdAt":"2010-02-02T19:14:42Z","updatedAt":"2017-05-15T08:15:36Z","forkCount":0,"livetimeInDays":3260,"contributers":[],"topics":["greasemonkey-script","obsolete","deprecated","javascript"],"usedLanguages":[{"name":"JavaScript","sizeInBytes":111636}]},{"id":561822,"owner":"trapd00r","name":"id3shit","fullRepoName":"trapd00r/id3shit","mainLanguage":"Perl","sizeInBytes":98,"createdAt":"2010-03-14T12:27:26Z","updatedAt":"2018-12-03T08:45:02Z","forkCount":0,"livetimeInDays":3220,"contributers":[],"topics":["perl","id3","cli","music","music-library"],"usedLanguages":[{"name":"Perl","sizeInBytes":361}]},{"id":566628,"owner":"KTamas","name":"8bittools","fullRepoName":"KTamas/8bittools","mainLanguage":"Ruby","sizeInBytes":96,"createdAt":"2010-03-17T14:15:26Z","updatedAt":"2017-03-29T11:03:36Z","forkCount":0,"livetimeInDays":3217,"contributers":[],"topics":["ruby","scraping","quickhack","unmaintained-dont-use"],"usedLanguages":[{"name":"Ruby","sizeInBytes":750}]},{"id":909912,"owner":"lukaselmer","name":"sun_spot_puzzle","fullRepoName":"lukaselmer/sun_spot_puzzle","mainLanguage":"Java","sizeInBytes":232,"createdAt":"2010-09-14T13:29:59Z","updatedAt":"2017-08-09T16:21:31Z","forkCount":0,"livetimeInDays":3036,"contributers":[],"topics":["java","hsr","embedded","sunspot","project","work","deploy"],"usedLanguages":[{"name":"Java","sizeInBytes":32779}]},{"id":910148,"owner":"lukaselmer","name":"sun_spot_puzzle_rails_server","fullRepoName":"lukaselmer/sun_spot_puzzle_rails_server","mainLanguage":"JavaScript","sizeInBytes":276,"createdAt":"2010-09-14T15:06:44Z","updatedAt":"2017-08-09T16:23:00Z","forkCount":0,"livetimeInDays":3036,"contributers":[],"topics":["ruby","ruby-on-rails","javascipt","jquery","sunspot","api","hsr","work","project"],"usedLanguages":[{"name":"JavaScript","sizeInBytes":217546},{"name":"Ruby","sizeInBytes":39053}]},{"id":910084,"owner":"lukaselmer","name":"sun_spot_http_transmitter","fullRepoName":"lukaselmer/sun_spot_http_transmitter","mainLanguage":"Java","sizeInBytes":104,"createdAt":"2010-09-14T14:39:32Z","updatedAt":"2017-08-09T16:35:51Z","forkCount":0,"livetimeInDays":3036,"contributers":[],"topics":["hsr","project","sunspot","java"],"usedLanguages":[{"name":"Java","sizeInBytes":6279}]},{"id":933534,"owner":"toshism","name":"django-random-image","fullRepoName":"toshism/django-random-image","mainLanguage":"Python","sizeInBytes":94,"createdAt":"2010-09-23T14:37:13Z","updatedAt":"2018-10-25T13:17:44Z","forkCount":1,"livetimeInDays":3027,"contributers":[],"topics":["django","python","image"],"usedLanguages":[{"name":"Python","sizeInBytes":630}]},{"id":871813,"owner":"TeMPOraL","name":"timelapse","fullRepoName":"TeMPOraL/timelapse","mainLanguage":"PHP","sizeInBytes":100,"createdAt":"2010-08-30T09:40:53Z","updatedAt":"2017-11-24T10:00:35Z","forkCount":0,"livetimeInDays":3051,"contributers":[],"topics":["timelapse","timelapse-videos","php"],"usedLanguages":[]},{"id":956893,"owner":"mmitch","name":"fluxbox-styles-mitch","fullRepoName":"mmitch/fluxbox-styles-mitch","mainLanguage":null,"sizeInBytes":100,"createdAt":"2010-10-02T17:33:20Z","updatedAt":"2018-12-30T23:07:52Z","forkCount":0,"livetimeInDays":3018,"contributers":[],"topics":["theme","style","fluxbox","wm","window-manager"],"usedLanguages":[]},{"id":961669,"owner":"tobiassjosten","name":"drush-sql-drop","fullRepoName":"tobiassjosten/drush-sql-drop","mainLanguage":null,"sizeInBytes":88,"createdAt":"2010-10-04T20:16:11Z","updatedAt":"2017-03-22T14:40:11Z","forkCount":0,"livetimeInDays":3016,"contributers":[],"topics":["php","drupal","drush"],"usedLanguages":[]},{"id":935535,"owner":"motus","name":"zerl","fullRepoName":"motus/zerl","mainLanguage":"Erlang","sizeInBytes":112,"createdAt":"2010-09-24T07:45:33Z","updatedAt":"2018-10-19T18:29:00Z","forkCount":0,"livetimeInDays":3026,"contributers":[],"topics":["erlang","erlang-framework","web-framework"],"usedLanguages":[{"name":"Erlang","sizeInBytes":2971},{"name":"Shell","sizeInBytes":493}]},{"id":973553,"owner":"faraday","name":"odp-extract","fullRepoName":"faraday/odp-extract","mainLanguage":"Python","sizeInBytes":108,"createdAt":"2010-10-08T23:55:11Z","updatedAt":"2018-07-26T18:17:55Z","forkCount":2,"livetimeInDays":3011,"contributers":[],"topics":["open-directory-project","natural-language-processing","data-mining"],"usedLanguages":[{"name":"Python","sizeInBytes":10215}]},{"id":974009,"owner":"wtnabe","name":"crontabwrap","fullRepoName":"wtnabe/crontabwrap","mainLanguage":"Ruby","sizeInBytes":92,"createdAt":"2010-10-09T06:55:08Z","updatedAt":"2017-05-08T14:35:06Z","forkCount":0,"livetimeInDays":3011,"contributers":[],"topics":["ruby","cli","cron"],"usedLanguages":[{"name":"Ruby","sizeInBytes":2514}]},{"id":475367,"owner":"lmartinking","name":"cdogs-sdl","fullRepoName":"lmartinking/cdogs-sdl","mainLanguage":"C","sizeInBytes":981,"createdAt":"2010-01-16T21:10:04Z","updatedAt":"2018-10-15T09:29:47Z","forkCount":6,"livetimeInDays":3277,"contributers":[],"topics":["sdl","game","arcade-game","c"],"usedLanguages":[{"name":"C","sizeInBytes":479453},{"name":"Objective-C","sizeInBytes":11215},{"name":"Shell","sizeInBytes":3913}]},{"id":994771,"owner":"mre","name":"jQuery.anchorfy","fullRepoName":"mre/jQuery.anchorfy","mainLanguage":"JavaScript","sizeInBytes":140,"createdAt":"2010-10-17T15:53:37Z","updatedAt":"2013-10-28T23:25:57Z","forkCount":0,"livetimeInDays":3003,"contributers":[],"topics":["anchors","html","jquery","javascript"],"usedLanguages":[{"name":"JavaScript","sizeInBytes":3569}]},{"id":969218,"owner":"faraday","name":"odp-tr30","fullRepoName":"faraday/odp-tr30","mainLanguage":null,"sizeInBytes":236,"createdAt":"2010-10-07T12:34:55Z","updatedAt":"2018-05-11T14:40:58Z","forkCount":1,"livetimeInDays":3013,"contributers":[],"topics":["dogal-dil-isleme","natural-language-processing","search-results-clustering","open-directory-project"],"usedLanguages":[]},{"id":1020756,"owner":"tomwhite","name":"blockclock","fullRepoName":"tomwhite/blockclock","mainLanguage":"HaXe","sizeInBytes":228,"createdAt":"2010-10-24T22:57:50Z","updatedAt":"2018-06-17T19:33:41Z","forkCount":0,"livetimeInDays":2995,"contributers":[],"topics":["visualization","time","geometry","mathematics","clock"],"usedLanguages":[{"name":"Haxe","sizeInBytes":105}]},{"id":1020982,"owner":"tyru","name":"grass.vim","fullRepoName":"tyru/grass.vim","mainLanguage":"VimL","sizeInBytes":88,"createdAt":"2010-10-25T00:51:49Z","updatedAt":"2014-06-11T19:27:02Z","forkCount":0,"livetimeInDays":2995,"contributers":[],"topics":["vim","grass","programming-language","syntax-highlighting","syntax"],"usedLanguages":[{"name":"Vim script","sizeInBytes":905}]},{"id":124918,"owner":"jmbr","name":"cl-buchberger","fullRepoName":"jmbr/cl-buchberger","mainLanguage":"Common Lisp","sizeInBytes":113,"createdAt":"2009-02-09T12:20:05Z","updatedAt":"2018-01-27T14:38:08Z","forkCount":0,"livetimeInDays":3618,"contributers":[],"topics":["computer-algebra","groebner-basis","common-lisp"],"usedLanguages":[{"name":"Common Lisp","sizeInBytes":28331}]},{"id":889877,"owner":"unhammer","name":"lyz","fullRepoName":"unhammer/lyz","mainLanguage":"JavaScript","sizeInBytes":228,"createdAt":"2010-09-05T18:41:33Z","updatedAt":"2017-02-21T10:26:22Z","forkCount":0,"livetimeInDays":3045,"contributers":[],"topics":["lyx","latex","extension"],"usedLanguages":[{"name":"JavaScript","sizeInBytes":81344}]},{"id":748376,"owner":"jasonv","name":"TicTacToe","fullRepoName":"jasonv/TicTacToe","mainLanguage":"Java","sizeInBytes":2688,"createdAt":"2010-06-30T04:42:29Z","updatedAt":"2018-11-11T05:50:54Z","forkCount":0,"livetimeInDays":3112,"contributers":[],"topics":["tic-tac-toe","tictactoe-game","java","ai"],"usedLanguages":[{"name":"Java","sizeInBytes":67020}]},{"id":1004243,"owner":"tkeemon","name":"Computer-Vision-and-AI","fullRepoName":"tkeemon/Computer-Vision-and-AI","mainLanguage":"Objective-C","sizeInBytes":125,"createdAt":"2010-10-19T02:47:53Z","updatedAt":"2018-12-13T03:45:47Z","forkCount":22,"livetimeInDays":3001,"contributers":[],"topics":["matlab","computer-vision","artificial-intelligence"],"usedLanguages":[{"name":"Objective-C","sizeInBytes":35873}]},{"id":844704,"owner":"spektom","name":"packtese","fullRepoName":"spektom/packtese","mainLanguage":null,"sizeInBytes":128,"createdAt":"2010-08-17T20:46:27Z","updatedAt":"2017-08-07T08:02:12Z","forkCount":0,"livetimeInDays":3064,"contributers":[],"topics":["eclipse","osgi","packaging"],"usedLanguages":[]},{"id":208430,"owner":"rvelhote","name":"GSoC-SWAT","fullRepoName":"rvelhote/GSoC-SWAT","mainLanguage":"JavaScript","sizeInBytes":756,"createdAt":"2009-05-23T17:09:53Z","updatedAt":"2018-04-11T19:42:48Z","forkCount":5,"livetimeInDays":3515,"contributers":[],"topics":["samba","swatches","python"],"usedLanguages":[{"name":"JavaScript","sizeInBytes":223914},{"name":"Python","sizeInBytes":158336}]},{"id":1087380,"owner":"vladocar","name":"CSS-Mobile-Reset","fullRepoName":"vladocar/CSS-Mobile-Reset","mainLanguage":null,"sizeInBytes":93,"createdAt":"2010-11-17T03:43:37Z","updatedAt":"2018-02-06T13:36:09Z","forkCount":10,"livetimeInDays":2972,"contributers":[],"topics":["css","css3","mobile","reset","reset-css"],"usedLanguages":[]},{"id":1035718,"owner":"PurpleBooth","name":"SABnzbs--Status","fullRepoName":"PurpleBooth/SABnzbs--Status","mainLanguage":"Ruby","sizeInBytes":732,"createdAt":"2010-10-29T19:03:17Z","updatedAt":"2017-02-16T21:30:40Z","forkCount":0,"livetimeInDays":2991,"contributers":[],"topics":["ruby","sabnzbd","notifications"],"usedLanguages":[{"name":"Ruby","sizeInBytes":347316},{"name":"JavaScript","sizeInBytes":10562}]},{"id":1037437,"owner":"thomasleveil","name":"b3-plugin-teamspeakmoh","fullRepoName":"thomasleveil/b3-plugin-teamspeakmoh","mainLanguage":"Python","sizeInBytes":108,"createdAt":"2010-10-30T13:40:23Z","updatedAt":"2018-12-25T18:34:55Z","forkCount":0,"livetimeInDays":2990,"contributers":[],"topics":["b3-plugin","bigbrotherbot","teamspeak"],"usedLanguages":[{"name":"Python","sizeInBytes":30783}]},{"id":185012,"owner":"dryruby","name":"adhoc.rb","fullRepoName":"dryruby/adhoc.rb","mainLanguage":"Ruby","sizeInBytes":112,"createdAt":"2009-04-25T00:40:21Z","updatedAt":"2018-09-12T11:15:15Z","forkCount":0,"livetimeInDays":3543,"contributers":[],"topics":["obsolete","unmaintained","ruby","rubygems"],"usedLanguages":[{"name":"Ruby","sizeInBytes":6634}]},{"id":1111734,"owner":"StuartMacKay","name":"translate-swf","fullRepoName":"StuartMacKay/translate-swf","mainLanguage":"Java","sizeInBytes":2964,"createdAt":"2010-11-25T10:29:46Z","updatedAt":"2018-12-03T00:49:46Z","forkCount":3,"livetimeInDays":2964,"contributers":[],"topics":["java","compiler","actionscript"],"usedLanguages":[{"name":"Java","sizeInBytes":411940}]},{"id":966183,"owner":"rel-eng","name":"QWmfPlugin","fullRepoName":"rel-eng/QWmfPlugin","mainLanguage":"C++","sizeInBytes":280,"createdAt":"2010-10-06T11:00:26Z","updatedAt":"2018-01-06T18:49:42Z","forkCount":0,"livetimeInDays":3014,"contributers":[],"topics":["qt","c-plus-plus","wmf","image","plugin"],"usedLanguages":[{"name":"C++","sizeInBytes":415950},{"name":"C","sizeInBytes":200660}]},{"id":177285,"owner":"dryruby","name":"openpgp.rb","fullRepoName":"dryruby/openpgp.rb","mainLanguage":"Ruby","sizeInBytes":294,"createdAt":"2009-04-16T04:31:14Z","updatedAt":"2018-09-12T10:09:42Z","forkCount":28,"livetimeInDays":3552,"contributers":[],"topics":["obsolete","unmaintained","ruby","rubygems"],"usedLanguages":[{"name":"Ruby","sizeInBytes":77581}]},{"id":814048,"owner":"dryruby","name":"i2p.rb","fullRepoName":"dryruby/i2p.rb","mainLanguage":"Ruby","sizeInBytes":768,"createdAt":"2010-08-03T07:47:15Z","updatedAt":"2018-11-07T05:00:41Z","forkCount":3,"livetimeInDays":3078,"contributers":[],"topics":["obsolete","unmaintained","ruby","rubygems"],"usedLanguages":[{"name":"Ruby","sizeInBytes":73997}]},{"id":1026967,"owner":"SuprDewd","name":"Chess","fullRepoName":"SuprDewd/Chess","mainLanguage":"C#","sizeInBytes":3539,"createdAt":"2010-10-26T22:06:10Z","updatedAt":"2017-01-31T07:05:32Z","forkCount":2,"livetimeInDays":2993,"contributers":[],"topics":["chess","chessboard","game","server","c-sharp","library"],"usedLanguages":[{"name":"C#","sizeInBytes":165070}]},{"id":639438,"owner":"Oregu","name":"schematic","fullRepoName":"Oregu/schematic","mainLanguage":"Haskell","sizeInBytes":104,"createdAt":"2010-04-30T06:04:45Z","updatedAt":"2017-04-10T19:00:55Z","forkCount":0,"livetimeInDays":3173,"contributers":[],"topics":["haskell","scheme","interpreter"],"usedLanguages":[{"name":"Haskell","sizeInBytes":5716}]},{"id":1142516,"owner":"StuartMacKay","name":"transform-cxx","fullRepoName":"StuartMacKay/transform-cxx","mainLanguage":"C","sizeInBytes":552,"createdAt":"2010-12-06T08:15:24Z","updatedAt":"2018-09-16T09:55:22Z","forkCount":2,"livetimeInDays":2953,"contributers":[],"topics":["c-plus-plus","flash","api"],"usedLanguages":[{"name":"C","sizeInBytes":1125785},{"name":"C++","sizeInBytes":766887}]},{"id":1142523,"owner":"StuartMacKay","name":"translate-cxx","fullRepoName":"StuartMacKay/translate-cxx","mainLanguage":"C++","sizeInBytes":164,"createdAt":"2010-12-06T08:17:44Z","updatedAt":"2017-07-31T11:50:37Z","forkCount":0,"livetimeInDays":2953,"contributers":[],"topics":["c-plus-plus","compiler","actionscript"],"usedLanguages":[{"name":"C++","sizeInBytes":334940},{"name":"C","sizeInBytes":34147}]},{"id":691636,"owner":"westy92","name":"Wii-Metronome","fullRepoName":"westy92/Wii-Metronome","mainLanguage":"C","sizeInBytes":2612,"createdAt":"2010-05-28T19:09:54Z","updatedAt":"2017-07-17T20:00:47Z","forkCount":0,"livetimeInDays":3145,"contributers":[],"topics":["wii","wii-homebrew","metronome","homebrew"],"usedLanguages":[{"name":"C","sizeInBytes":128021},{"name":"C++","sizeInBytes":112901}]},{"id":370172,"owner":"themech","name":"ms2txt","fullRepoName":"themech/ms2txt","mainLanguage":"Python","sizeInBytes":338,"createdAt":"2009-11-12T12:45:24Z","updatedAt":"2018-11-08T06:50:32Z","forkCount":6,"livetimeInDays":3342,"contributers":[],"topics":["python","trading","data-processing","converter"],"usedLanguages":[{"name":"Python","sizeInBytes":12224}]},{"id":1056773,"owner":"gergoerdi","name":"language-java-classfile","fullRepoName":"gergoerdi/language-java-classfile","mainLanguage":"Haskell","sizeInBytes":103,"createdAt":"2010-11-06T13:22:59Z","updatedAt":"2016-12-23T02:42:13Z","forkCount":0,"livetimeInDays":2983,"contributers":[],"topics":["haskell","java","classfile"],"usedLanguages":[{"name":"Haskell","sizeInBytes":16792},{"name":"Java","sizeInBytes":614}]},{"id":1155877,"owner":"floehopper","name":"installd","fullRepoName":"floehopper/installd","mainLanguage":"Ruby","sizeInBytes":12016,"createdAt":"2010-12-10T10:58:23Z","updatedAt":"2018-08-19T11:10:30Z","forkCount":0,"livetimeInDays":2949,"contributers":[],"topics":["ios","iphone","social-network"],"usedLanguages":[{"name":"Ruby","sizeInBytes":152147},{"name":"JavaScript","sizeInBytes":69256}]},{"id":1012837,"owner":"thodg","name":"cl-sh","fullRepoName":"thodg/cl-sh","mainLanguage":"Common Lisp","sizeInBytes":96,"createdAt":"2010-10-21T17:44:43Z","updatedAt":"2017-06-06T11:28:57Z","forkCount":0,"livetimeInDays":2999,"contributers":[],"topics":["shell","unix","posix"],"usedLanguages":[{"name":"Common Lisp","sizeInBytes":8255}]},{"id":401172,"owner":"davidlim","name":"InStyle","fullRepoName":"davidlim/InStyle","mainLanguage":"PHP","sizeInBytes":115,"createdAt":"2009-12-06T00:42:07Z","updatedAt":"2017-02-12T00:05:35Z","forkCount":2,"livetimeInDays":3318,"contributers":[],"topics":["php","email","css","inline-styles"],"usedLanguages":[{"name":"PHP","sizeInBytes":40791}]},{"id":1183107,"owner":"vladocar","name":"CSS3-Chat-Bubble","fullRepoName":"vladocar/CSS3-Chat-Bubble","mainLanguage":null,"sizeInBytes":96,"createdAt":"2010-12-20T01:21:46Z","updatedAt":"2018-02-06T13:37:47Z","forkCount":0,"livetimeInDays":2939,"contributers":[],"topics":["css","css3","chat-bubble"],"usedLanguages":[]},{"id":558339,"owner":"tobiassjosten","name":"reactions","fullRepoName":"tobiassjosten/reactions","mainLanguage":"PHP","sizeInBytes":151,"createdAt":"2010-03-11T22:17:56Z","updatedAt":"2017-03-22T14:41:53Z","forkCount":0,"livetimeInDays":3223,"contributers":[],"topics":["php","drupal","module"],"usedLanguages":[{"name":"PHP","sizeInBytes":16228}]},{"id":1463794,"owner":"symphonists","name":"meta_section","fullRepoName":"symphonists/meta_section","mainLanguage":"PHP","sizeInBytes":271,"createdAt":"2011-03-10T14:50:44Z","updatedAt":"2017-05-23T01:40:16Z","forkCount":1,"livetimeInDays":2859,"contributers":[],"topics":["symphony-cms","symphony-cms-extension","symphony-cms-ui"],"usedLanguages":[]},{"id":575081,"owner":"jweyrich","name":"proxylib","fullRepoName":"jweyrich/proxylib","mainLanguage":"C","sizeInBytes":112,"createdAt":"2010-03-23T02:48:21Z","updatedAt":"2017-03-15T13:20:13Z","forkCount":0,"livetimeInDays":3211,"contributers":[],"topics":["socks4a","proxy","proxy-server","asio","asynchronous","c-plus-plus"],"usedLanguages":[{"name":"C","sizeInBytes":17813},{"name":"C++","sizeInBytes":13708}]},{"id":1197116,"owner":"KTamas","name":"bingo-nodejs-unstable-pre-alpha","fullRepoName":"KTamas/bingo-nodejs-unstable-pre-alpha","mainLanguage":"JavaScript","sizeInBytes":800,"createdAt":"2010-12-25T12:24:21Z","updatedAt":"2017-03-29T11:03:07Z","forkCount":1,"livetimeInDays":2934,"contributers":[],"topics":["javascript","nodejs","experiment","unmaintained-dont-use"],"usedLanguages":[{"name":"JavaScript","sizeInBytes":183997}]},{"id":1226342,"owner":"Carlmundo","name":"Word-RevisionSaves","fullRepoName":"Carlmundo/Word-RevisionSaves","mainLanguage":null,"sizeInBytes":88,"createdAt":"2011-01-06T13:31:59Z","updatedAt":"2017-05-24T14:16:23Z","forkCount":0,"livetimeInDays":2922,"contributers":[],"topics":["word","office","version-control"],"usedLanguages":[]},{"id":503850,"owner":"splitbrain","name":"WePing","fullRepoName":"splitbrain/WePing","mainLanguage":"PHP","sizeInBytes":112,"createdAt":"2010-02-05T12:58:47Z","updatedAt":"2017-02-06T15:53:36Z","forkCount":2,"livetimeInDays":3257,"contributers":[],"topics":["obsolete","php","social-media","abandoned"],"usedLanguages":[{"name":"PHP","sizeInBytes":32250},{"name":"JavaScript","sizeInBytes":1340}]},{"id":1233420,"owner":"taktoa","name":"OscFinder","fullRepoName":"taktoa/OscFinder","mainLanguage":"Haskell","sizeInBytes":756,"createdAt":"2011-01-08T18:22:29Z","updatedAt":"2014-05-14T14:43:30Z","forkCount":0,"livetimeInDays":2920,"contributers":[],"topics":["haskell","oscillator","calculator"],"usedLanguages":[{"name":"Haskell","sizeInBytes":5560}]},{"id":854660,"owner":"DE-IBH","name":"mupe","fullRepoName":"DE-IBH/mupe","mainLanguage":null,"sizeInBytes":178,"createdAt":"2010-08-22T12:46:20Z","updatedAt":"2018-09-21T21:43:25Z","forkCount":1,"livetimeInDays":3059,"contributers":[],"topics":["perl","802-11","obsolete"],"usedLanguages":[]},{"id":494238,"owner":"unhammer","name":"lfgalign","fullRepoName":"unhammer/lfgalign","mainLanguage":"Prolog","sizeInBytes":24452,"createdAt":"2010-01-29T21:10:34Z","updatedAt":"2017-02-21T10:26:07Z","forkCount":0,"livetimeInDays":3264,"contributers":[],"topics":["lfg","alignment","treebank","syntax","paper"],"usedLanguages":[{"name":"Prolog","sizeInBytes":3186037},{"name":"TeX","sizeInBytes":457472},{"name":"Common Lisp","sizeInBytes":113414},{"name":"Python","sizeInBytes":2365},{"name":"Shell","sizeInBytes":1768},{"name":"Perl","sizeInBytes":37}]},{"id":15981794,"owner":"AbhishekGhosh","name":"Pacemaker","fullRepoName":"AbhishekGhosh/Pacemaker","mainLanguage":null,"sizeInBytes":100,"createdAt":"2014-01-16T21:40:16Z","updatedAt":"2017-05-28T16:50:58Z","forkCount":0,"livetimeInDays":1816,"contributers":[],"topics":["pacemaker","opensource","abhishekghosh"],"usedLanguages":[]},{"id":1276942,"owner":"MatthewCallis","name":"Canvas-Graphs","fullRepoName":"MatthewCallis/Canvas-Graphs","mainLanguage":"PHP","sizeInBytes":112,"createdAt":"2011-01-21T02:23:32Z","updatedAt":"2018-11-12T22:48:00Z","forkCount":0,"livetimeInDays":2907,"contributers":[],"topics":["php","wordpre","wordpress-plugin","charts","graphs"],"usedLanguages":[{"name":"PHP","sizeInBytes":14657},{"name":"JavaScript","sizeInBytes":7455}]},{"id":1111697,"owner":"StuartMacKay","name":"cookbook-swf","fullRepoName":"StuartMacKay/cookbook-swf","mainLanguage":"Java","sizeInBytes":574,"createdAt":"2010-11-25T10:10:24Z","updatedAt":"2017-07-31T11:50:00Z","forkCount":1,"livetimeInDays":2964,"contributers":[],"topics":["swf","java","cookbooks","flash"],"usedLanguages":[{"name":"Java","sizeInBytes":115767},{"name":"ActionScript","sizeInBytes":94}]},{"id":1279710,"owner":"ronnix","name":"wordcloud","fullRepoName":"ronnix/wordcloud","mainLanguage":"Python","sizeInBytes":116,"createdAt":"2011-01-21T19:47:42Z","updatedAt":"2018-03-08T15:02:02Z","forkCount":0,"livetimeInDays":2907,"contributers":[],"topics":["competitive-programming","python","pylons"],"usedLanguages":[{"name":"Python","sizeInBytes":22237}]},{"id":1285986,"owner":"aeurielesn","name":"tju","fullRepoName":"aeurielesn/tju","mainLanguage":"C++","sizeInBytes":148,"createdAt":"2011-01-23T23:16:45Z","updatedAt":"2017-03-08T14:11:03Z","forkCount":4,"livetimeInDays":2904,"contributers":[],"topics":["competitive-programming","tju","tju-solutions"],"usedLanguages":[{"name":"C++","sizeInBytes":18596}]},{"id":1200173,"owner":"pioz","name":"rplot","fullRepoName":"pioz/rplot","mainLanguage":"Ruby","sizeInBytes":256,"createdAt":"2010-12-27T10:02:32Z","updatedAt":"2017-08-03T01:19:59Z","forkCount":0,"livetimeInDays":2932,"contributers":[],"topics":["ruby","libplot","plot"],"usedLanguages":[{"name":"Ruby","sizeInBytes":53885},{"name":"C","sizeInBytes":35583}]},{"id":1228666,"owner":"iap-csharp","name":"iap-csharp.github.com","fullRepoName":"iap-csharp/iap-csharp.github.com","mainLanguage":null,"sizeInBytes":4468,"createdAt":"2011-01-07T05:23:07Z","updatedAt":"2017-02-01T07:16:45Z","forkCount":0,"livetimeInDays":2921,"contributers":[],"topics":["csharp","class","lectures"],"usedLanguages":[]},{"id":1300400,"owner":"ribtoks","name":"LongInt","fullRepoName":"ribtoks/LongInt","mainLanguage":"C#","sizeInBytes":148,"createdAt":"2011-01-27T20:30:19Z","updatedAt":"2016-03-02T13:56:51Z","forkCount":0,"livetimeInDays":2901,"contributers":[],"topics":["c-sharp","arithmetic","rsa","rsa-signature","numerical-calculations"],"usedLanguages":[{"name":"C#","sizeInBytes":141517}]},{"id":1308821,"owner":"saschpe","name":"kidcat","fullRepoName":"saschpe/kidcat","mainLanguage":"C","sizeInBytes":116,"createdAt":"2011-01-30T12:45:16Z","updatedAt":"2018-08-21T20:01:33Z","forkCount":0,"livetimeInDays":2898,"contributers":[],"topics":["posix","c","makefile","syscall","pthread","socket"],"usedLanguages":[{"name":"C","sizeInBytes":25277}]},{"id":921204,"owner":"balupton","name":"balphp","fullRepoName":"balupton/balphp","mainLanguage":"PHP","sizeInBytes":1433,"createdAt":"2010-09-18T19:17:52Z","updatedAt":"2018-07-05T06:55:18Z","forkCount":2,"livetimeInDays":3032,"contributers":[],"topics":["php-framework","ecommerce-framework","php","unsupported"],"usedLanguages":[{"name":"PHP","sizeInBytes":1083449}]},{"id":1155550,"owner":"jeantessier","name":"TwoStageGuiceProvider","fullRepoName":"jeantessier/TwoStageGuiceProvider","mainLanguage":"Java","sizeInBytes":104,"createdAt":"2010-12-10T07:42:21Z","updatedAt":"2016-12-16T18:35:12Z","forkCount":0,"livetimeInDays":2949,"contributers":[],"topics":["java","guice","article"],"usedLanguages":[{"name":"Java","sizeInBytes":30288},{"name":"Perl","sizeInBytes":5359}]},{"id":1332404,"owner":"insin","name":"djangoffice","fullRepoName":"insin/djangoffice","mainLanguage":"Python","sizeInBytes":376,"createdAt":"2011-02-05T19:58:54Z","updatedAt":"2018-10-05T19:21:10Z","forkCount":4,"livetimeInDays":2892,"contributers":[],"topics":["django","project-management","crm","unmaintained"],"usedLanguages":[{"name":"Python","sizeInBytes":282890},{"name":"JavaScript","sizeInBytes":136958}]},{"id":1348729,"owner":"RaVbaker","name":"search_in_memory_php","fullRepoName":"RaVbaker/search_in_memory_php","mainLanguage":"PHP","sizeInBytes":108,"createdAt":"2011-02-09T23:52:54Z","updatedAt":"2015-02-01T13:55:22Z","forkCount":0,"livetimeInDays":2887,"contributers":[],"topics":["information-retrieval","full-text-search","php"],"usedLanguages":[{"name":"PHP","sizeInBytes":57008}]},{"id":1351515,"owner":"marcelog","name":"Pakman","fullRepoName":"marcelog/Pakman","mainLanguage":"C","sizeInBytes":123,"createdAt":"2011-02-10T17:25:11Z","updatedAt":"2017-11-13T14:01:47Z","forkCount":0,"livetimeInDays":2887,"contributers":[],"topics":["c","freebsd","package-manager"],"usedLanguages":[{"name":"C","sizeInBytes":97697}]},{"id":1283908,"owner":"aeurielesn","name":"codeforces","fullRepoName":"aeurielesn/codeforces","mainLanguage":"C++","sizeInBytes":120,"createdAt":"2011-01-23T06:04:14Z","updatedAt":"2017-03-08T14:10:13Z","forkCount":2,"livetimeInDays":2905,"contributers":[],"topics":["competitive-programming","codeforces","codeforces-solutions"],"usedLanguages":[{"name":"C++","sizeInBytes":23624},{"name":"Ruby","sizeInBytes":80}]},{"id":852434,"owner":"pvande","name":"Test-Mini-Unit","fullRepoName":"pvande/Test-Mini-Unit","mainLanguage":"Perl","sizeInBytes":264,"createdAt":"2010-08-21T01:00:03Z","updatedAt":"2014-09-08T21:12:11Z","forkCount":1,"livetimeInDays":3060,"contributers":[],"topics":["perl","test-framework","preprocessor"],"usedLanguages":[{"name":"Perl","sizeInBytes":37773}]},{"id":1383661,"owner":"marcelog","name":"ICSUDA","fullRepoName":"marcelog/ICSUDA","mainLanguage":"Java","sizeInBytes":272,"createdAt":"2011-02-18T18:59:22Z","updatedAt":"2017-10-21T14:52:04Z","forkCount":1,"livetimeInDays":2879,"contributers":[],"topics":["java","icq","messaging","messenger"],"usedLanguages":[{"name":"Java","sizeInBytes":85890}]},{"id":1383754,"owner":"marcelog","name":"Boot-Sector-Tools","fullRepoName":"marcelog/Boot-Sector-Tools","mainLanguage":"Assembly","sizeInBytes":96,"createdAt":"2011-02-18T19:24:28Z","updatedAt":"2017-10-21T14:51:37Z","forkCount":3,"livetimeInDays":2879,"contributers":[],"topics":["a86","assembly","boot","x86"],"usedLanguages":[{"name":"Assembly","sizeInBytes":16937}]},{"id":1389368,"owner":"ardalahmet","name":"CE242--Spring-09","fullRepoName":"ardalahmet/CE242--Spring-09","mainLanguage":"C++","sizeInBytes":156,"createdAt":"2011-02-20T14:58:33Z","updatedAt":"2018-11-07T21:55:05Z","forkCount":0,"livetimeInDays":2877,"contributers":[],"topics":["c-plus-plus","algorithms","algorithms-datastructures","algorithms-and-data-structures","data-structures","datastructures-algorithms","algorithms-implemented","c","college","college-assignment","computer-science","cs","computer-engineering","binary-trees","sorting-algorithms","sorting","sorting-algorithms-implemented"],"usedLanguages":[{"name":"C++","sizeInBytes":150279},{"name":"C","sizeInBytes":20718}]},{"id":992058,"owner":"dkruchinin","name":"pppd-ldap","fullRepoName":"dkruchinin/pppd-ldap","mainLanguage":"C","sizeInBytes":132,"createdAt":"2010-10-16T07:30:02Z","updatedAt":"2017-05-09T18:42:16Z","forkCount":0,"livetimeInDays":3004,"contributers":[],"topics":["c","ppp","ldap","mschap"],"usedLanguages":[{"name":"C","sizeInBytes":43652}]},{"id":1415179,"owner":"arminrosu","name":"WP-Reset-Post-IDs","fullRepoName":"arminrosu/WP-Reset-Post-IDs","mainLanguage":"PHP","sizeInBytes":92,"createdAt":"2011-02-26T16:46:57Z","updatedAt":"2018-07-01T16:30:42Z","forkCount":0,"livetimeInDays":2871,"contributers":[],"topics":["wordpress","wordpress-tool","wordpress-utility"],"usedLanguages":[{"name":"PHP","sizeInBytes":4519}]},{"id":1344837,"owner":"edlau","name":"GABot","fullRepoName":"edlau/GABot","mainLanguage":"C++","sizeInBytes":3060,"createdAt":"2011-02-09T03:14:42Z","updatedAt":"2013-12-25T22:29:41Z","forkCount":0,"livetimeInDays":2888,"contributers":[],"topics":["school","artificial-intelligence","genetic-algorithm","computer-science"],"usedLanguages":[{"name":"C++","sizeInBytes":127347},{"name":"C","sizeInBytes":27175},{"name":"Perl","sizeInBytes":113}]},{"id":1418207,"owner":"c1982","name":"Mikrogi","fullRepoName":"c1982/Mikrogi","mainLanguage":"C#","sizeInBytes":175,"createdAt":"2011-02-27T15:37:44Z","updatedAt":"2018-09-12T09:26:07Z","forkCount":4,"livetimeInDays":2870,"contributers":[],"topics":["mikrotik","c-sharp","api"],"usedLanguages":[{"name":"C#","sizeInBytes":16547}]},{"id":1379921,"owner":"renderedtext","name":"jquery-placeholders","fullRepoName":"renderedtext/jquery-placeholders","mainLanguage":"JavaScript","sizeInBytes":91,"createdAt":"2011-02-17T21:22:25Z","updatedAt":"2018-02-01T14:30:26Z","forkCount":2,"livetimeInDays":2880,"contributers":[],"topics":["jquery","javascript","semaphore-open-source"],"usedLanguages":[{"name":"JavaScript","sizeInBytes":1991}]},{"id":1288141,"owner":"relson","name":"tccp42","fullRepoName":"relson/tccp42","mainLanguage":"Java","sizeInBytes":6216,"createdAt":"2011-01-24T15:57:08Z","updatedAt":"2017-04-04T13:40:00Z","forkCount":0,"livetimeInDays":2904,"contributers":[],"topics":["java","google-appengine","unip","jee"],"usedLanguages":[{"name":"Java","sizeInBytes":15724},{"name":"JavaScript","sizeInBytes":10499}]},{"id":1427892,"owner":"segabor","name":"NE2K","fullRepoName":"segabor/NE2K","mainLanguage":"Objective-C","sizeInBytes":124,"createdAt":"2011-03-01T21:11:05Z","updatedAt":"2018-12-06T12:20:40Z","forkCount":0,"livetimeInDays":2868,"contributers":[],"topics":["nextstep","ne2000","ne2k","openstep"],"usedLanguages":[{"name":"Objective-C","sizeInBytes":32071},{"name":"C","sizeInBytes":19896}]},{"id":165728,"owner":"symphonists","name":"calendaroverlay","fullRepoName":"symphonists/calendaroverlay","mainLanguage":"PHP","sizeInBytes":235,"createdAt":"2009-04-02T01:28:31Z","updatedAt":"2019-01-03T00:36:27Z","forkCount":1,"livetimeInDays":3566,"contributers":[],"topics":["symphony-cms","symphony-cms-extension","symphony-cms-deprecated"],"usedLanguages":[{"name":"PHP","sizeInBytes":1228}]},{"id":1384594,"owner":"MasterXen","name":"indextank-csharp","fullRepoName":"MasterXen/indextank-csharp","mainLanguage":"C#","sizeInBytes":344,"createdAt":"2011-02-18T23:06:22Z","updatedAt":"2013-11-02T22:58:12Z","forkCount":2,"livetimeInDays":2878,"contributers":[],"topics":["c-sharp","indextank","dotnet"],"usedLanguages":[{"name":"C#","sizeInBytes":8387}]},{"id":1298529,"owner":"dg","name":"texy-editor","fullRepoName":"dg/texy-editor","mainLanguage":"PHP","sizeInBytes":572,"createdAt":"2011-01-27T09:54:37Z","updatedAt":"2017-06-13T09:40:05Z","forkCount":3,"livetimeInDays":2901,"contributers":[],"topics":["php","texy","editor"],"usedLanguages":[{"name":"PHP","sizeInBytes":125893},{"name":"JavaScript","sizeInBytes":3215}]},{"id":852415,"owner":"mkoloberdin","name":"z80ex","fullRepoName":"mkoloberdin/z80ex","mainLanguage":"C","sizeInBytes":172,"createdAt":"2010-08-21T00:35:46Z","updatedAt":"2018-10-25T19:18:02Z","forkCount":0,"livetimeInDays":3060,"contributers":[],"topics":["z80","cpu","emulation"],"usedLanguages":[{"name":"C","sizeInBytes":374455},{"name":"Perl","sizeInBytes":17549}]},{"id":1469285,"owner":"piouPiouM","name":"compass-completion","fullRepoName":"piouPiouM/compass-completion","mainLanguage":"Shell","sizeInBytes":96,"createdAt":"2011-03-11T19:38:28Z","updatedAt":"2016-03-04T03:28:47Z","forkCount":0,"livetimeInDays":2858,"contributers":[],"topics":["shell","bash-completion","compass"],"usedLanguages":[{"name":"Shell","sizeInBytes":4853}]},{"id":236914,"owner":"symphonists","name":"htmlformatter","fullRepoName":"symphonists/htmlformatter","mainLanguage":"PHP","sizeInBytes":2084,"createdAt":"2009-06-26T12:26:55Z","updatedAt":"2017-06-06T02:10:38Z","forkCount":1,"livetimeInDays":3481,"contributers":[],"topics":["symphony-cms","symphony-cms-extension","symphony-cms-formatter"],"usedLanguages":[{"name":"PHP","sizeInBytes":43280},{"name":"JavaScript","sizeInBytes":27947}]},{"id":1480858,"owner":"EdlinOrg","name":"phpmodgraph","fullRepoName":"EdlinOrg/phpmodgraph","mainLanguage":"PHP","sizeInBytes":136,"createdAt":"2011-03-15T00:53:10Z","updatedAt":"2018-03-28T08:13:36Z","forkCount":0,"livetimeInDays":2854,"contributers":[],"topics":["php","graph","callgraph"],"usedLanguages":[{"name":"PHP","sizeInBytes":21379},{"name":"Shell","sizeInBytes":358}]},{"id":1496148,"owner":"splitbrain","name":"ook","fullRepoName":"splitbrain/ook","mainLanguage":"PHP","sizeInBytes":120,"createdAt":"2011-03-18T13:46:54Z","updatedAt":"2018-11-03T08:08:34Z","forkCount":7,"livetimeInDays":2851,"contributers":[],"topics":["php","ook","brainfuck"],"usedLanguages":[{"name":"PHP","sizeInBytes":11343}]},{"id":1463537,"owner":"oroszgy","name":"radixtree","fullRepoName":"oroszgy/radixtree","mainLanguage":"JavaScript","sizeInBytes":340,"createdAt":"2011-03-10T13:39:34Z","updatedAt":"2018-09-14T15:09:52Z","forkCount":1,"livetimeInDays":2859,"contributers":[],"topics":["java","data-structures","radix-tree","radix-trie","suffix-tree","javascript"],"usedLanguages":[{"name":"JavaScript","sizeInBytes":70383},{"name":"Java","sizeInBytes":41895}]},{"id":755617,"owner":"Mischback","name":"oUF_PredatorSimple","fullRepoName":"Mischback/oUF_PredatorSimple","mainLanguage":"Lua","sizeInBytes":120,"createdAt":"2010-07-03T22:07:12Z","updatedAt":"2018-03-15T11:58:03Z","forkCount":0,"livetimeInDays":3108,"contributers":[],"topics":["lua","world-of-warcraft","worldofwarcraft","not-maintained","ouf"],"usedLanguages":[{"name":"Lua","sizeInBytes":70815}]},{"id":1556225,"owner":"ohtorii","name":"google_suggest","fullRepoName":"ohtorii/google_suggest","mainLanguage":"JavaScript","sizeInBytes":92,"createdAt":"2011-04-01T16:09:58Z","updatedAt":"2018-09-30T11:19:18Z","forkCount":0,"livetimeInDays":2837,"contributers":[],"topics":["hidemaru","google-suggestions","javascript"],"usedLanguages":[{"name":"JavaScript","sizeInBytes":133}]},{"id":1561053,"owner":"splitbrain","name":"musicbrowser","fullRepoName":"splitbrain/musicbrowser","mainLanguage":"PHP","sizeInBytes":124,"createdAt":"2011-04-02T22:27:07Z","updatedAt":"2017-06-09T12:05:36Z","forkCount":0,"livetimeInDays":2835,"contributers":[],"topics":["php","mp3","mp3-playlist"],"usedLanguages":[{"name":"PHP","sizeInBytes":4339}]},{"id":1563760,"owner":"julianwachholz","name":"jsbimaru","fullRepoName":"julianwachholz/jsbimaru","mainLanguage":"JavaScript","sizeInBytes":204,"createdAt":"2011-04-03T18:17:35Z","updatedAt":"2017-08-25T09:02:21Z","forkCount":0,"livetimeInDays":2835,"contributers":[],"topics":["javascript","jquery","bimaru","battleship","battleship-game"],"usedLanguages":[{"name":"JavaScript","sizeInBytes":15031},{"name":"PHP","sizeInBytes":191}]}]